nomad/__init__.py
nomad/api/__init__.py
nomad/api/acl.py
nomad/api/agent.py
nomad/api/allocation.py
nomad/api/allocations.py
nomad/api/base.py
nomad/api/client.py
nomad/api/deployment.py
nomad/api/deployments.py
nomad/api/evaluation.py
nomad/api/evaluations.py
nomad/api/event.py
nomad/api/exceptions.py
nomad/api/job.py
nomad/api/jobs.py
nomad/api/metrics.py
nomad/api/namespace.py
nomad/api/namespaces.py
nomad/api/node.py
nomad/api/nodes.py
nomad/api/operator.py
nomad/api/regions.py
nomad/api/scaling.py
nomad/api/search.py
nomad/api/sentinel.py
nomad/api/status.py
nomad/api/system.py
nomad/api/validate.py
nomad/api/variable.py
nomad/api/variables.py
python_nomad-2.0.1.dist-info/LICENSE
python_nomad-2.0.1.dist-info/METADATA
python_nomad-2.0.1.dist-info/WHEEL
python_nomad-2.0.1.dist-info/top_level.txt
python_nomad-2.0.1.dist-info/RECORD
