Metadata-Version: 2.1
Name: python-nomad
Version: 2.0.1
Summary: Client library for Hashicorp Nomad
Home-page: http://github.com/jrxfive/python-nomad
Author: jrxfive
Author-email: jrxfive@gmail.com
License: MIT
Keywords: nomad hashicorp client
Classifier: Development Status :: 5 - Production/Stable
Classifier: Intended Audience :: Developers
Classifier: License :: OSI Approved :: MIT License
Classifier: Programming Language :: Python :: 3.7
Classifier: Programming Language :: Python :: 3.8
Classifier: Programming Language :: Python :: 3.9
Classifier: Programming Language :: Python :: 3.10
Classifier: Programming Language :: Python :: 3.11
License-File: LICENSE
Requires-Dist: requests
